autocat/VERSION.txt
autocat/__init__.py
autocat/adsorption.py
autocat/base.py
autocat/bulk.py
autocat/saa.py
autocat/surface.py
autocat/utils.py
autocat/data/__init__.py
autocat/data/hhi/__init__.py
autocat/data/hhi/hhi_p.json
autocat/data/hhi/hhi_r.json
autocat/data/intermediates/__init__.py
autocat/data/intermediates/nrr.py
autocat/data/intermediates/orr.py
autocat/data/lattice_parameters/__init__.py
autocat/data/lattice_parameters/bulk_beefvdw_fd.json
autocat/data/lattice_parameters/bulk_beefvdw_pw.json
autocat/data/lattice_parameters/bulk_pbe_fd.json
autocat/data/lattice_parameters/bulk_pbe_pw.json
autocat/data/segregation_energies/__init__.py
autocat/data/segregation_energies/raban1999.json
autocat/data/segregation_energies/rao2020.json
autocat/learning/__init__.py
autocat/learning/featurizers.py
autocat/learning/predictors.py
autocat/learning/sequential.py
autocat-2022.8.5.dist-info/LICENSE
autocat-2022.8.5.dist-info/METADATA
autocat-2022.8.5.dist-info/WHEEL
autocat-2022.8.5.dist-info/top_level.txt
autocat-2022.8.5.dist-info/RECORD
