Metadata-Version: 2.1
Name: autocat
Version: 2022.8.5
Summary: Tools for automated generation of catalyst structures and sequential learning
Home-page: https://github.com/aced-differentiate/auto_cat
Author: Lance Kavalsky
Author-email: lkavalsk@andrew.cmu.edu
License: MIT
Classifier: Development Status :: 3 - Alpha
Classifier: Programming Language :: Python :: 3.9
License-File: LICENSE
Requires-Dist: numpy
Requires-Dist: ase
Requires-Dist: pymatgen
Requires-Dist: fire
Requires-Dist: matminer
Requires-Dist: dscribe
Requires-Dist: prettytable
Requires-Dist: joblib
